stressberry/__about__.py
stressberry/__init__.py
stressberry/cli.py
stressberry/main.py
stressberry/cli/__init__.py
stressberry/cli/helpers.py
stressberry/cli/plot.py
stressberry/cli/run.py
stressberry-0.3.3.dist-info/LICENSE
stressberry-0.3.3.dist-info/METADATA
stressberry-0.3.3.dist-info/WHEEL
stressberry-0.3.3.dist-info/entry_points.txt
stressberry-0.3.3.dist-info/top_level.txt
stressberry-0.3.3.dist-info/RECORD
