Metadata-Version: 2.1
Name: stressberry
Version: 0.3.3
Summary: Stress tests for the Raspberry Pi
Home-page: https://github.com/nschloe/stressberry
Author: Nico Schlömer
Author-email: nico.schloemer@gmail.com
License: GPL-3.0-or-later
Project-URL: Code, https://github.com/nschloe/stressberry
Project-URL: Issues, https://github.com/nschloe/stressberry/issues
Platform: UNKNOWN
Classifier: Development Status :: 4 - Beta
Classifier: License :: OSI Approved :: GNU General Public License v3 or later (GPLv3+)
Classifier: Operating System :: OS Independent
Classifier: Programming Language :: Python
Classifier: Programming Language :: Python :: 3
Classifier: Programming Language :: Python :: 3.6
Classifier: Programming Language :: Python :: 3.7
Classifier: Programming Language :: Python :: 3.8
Classifier: Programming Language :: Python :: 3.9
Classifier: Topic :: Utilities
Requires-Python: >=3.6
Requires-Dist: dufte
Requires-Dist: matplotlib
Requires-Dist: pyyaml
Requires-Dist: importlib-metadata ; python_version < "3.8"
